storeonce_client/__init__.py
storeonce_client/configuration.py
storeonce_client/rest.py
storeonce_client/platform/__init__.py
storeonce_client/platform/alerts_and_events/__init__.py
storeonce_client/platform/alerts_and_events/api_client.py
storeonce_client/platform/alerts_and_events/api/__init__.py
storeonce_client/platform/alerts_and_events/api/alerts_api.py
storeonce_client/platform/alerts_and_events/models/__init__.py
storeonce_client/platform/alerts_and_events/models/alerts_entries.py
storeonce_client/platform/alerts_and_events/models/alerts_entry.py
storeonce_client/platform/alerts_and_events/models/associated_resource.py
storeonce_client/platform/alerts_and_events/models/association.py
storeonce_client/platform/alerts_and_events/models/auto_prune_months_payload.py
storeonce_client/platform/alerts_and_events/models/catalog_key_pair.py
storeonce_client/platform/alerts_and_events/models/change_log.py
storeonce_client/platform/alerts_and_events/models/count_payload.py
storeonce_client/platform/alerts_and_events/models/delete_status.py
storeonce_client/platform/alerts_and_events/models/event_details.py
storeonce_client/platform/alerts_and_events/models/events_entries.py
storeonce_client/platform/alerts_and_events/models/events_entry.py
storeonce_client/platform/alerts_and_events/models/message_info.py
storeonce_client/platform/alerts_and_events/models/message_info_arg_wrapper.py
storeonce_client/platform/alerts_and_events/models/message_info_wrapper.py
storeonce_client/platform/alerts_and_events/models/progress_update.py
storeonce_client/platform/alerts_and_events/models/service_event_details.py
storeonce_client/platform/asynchronous_tasks/__init__.py
storeonce_client/platform/asynchronous_tasks/api_client.py
storeonce_client/platform/asynchronous_tasks/api/__init__.py
storeonce_client/platform/asynchronous_tasks/api/asynchronous_task_management_api.py
storeonce_client/platform/asynchronous_tasks/models/__init__.py
storeonce_client-1.4.1.1.8.dist-info/LICENSE
storeonce_client-1.4.1.1.8.dist-info/METADATA
storeonce_client-1.4.1.1.8.dist-info/WHEEL
storeonce_client-1.4.1.1.8.dist-info/top_level.txt
storeonce_client-1.4.1.1.8.dist-info/RECORD
