Metadata-Version: 2.1
Name: storeonce-client
Version: 1.4.1.1.8
Summary: A StoreOnce REST client SDK
Home-page: UNKNOWN
Author: Hewlett Packard Enterprise Development LP
License: MIT
Keywords: Swagger,StoreOnce,REST,SDK
Platform: UNKNOWN
Classifier: Programming Language :: Python :: Implementation :: CPython
Classifier: Programming Language :: Python :: 3.7
Classifier: Programming Language :: Python :: 2
Classifier: Programming Language :: Python
Classifier: License :: OSI Approved :: MIT License
Classifier: Development Status :: 4 - Beta
Classifier: Programming Language :: Python :: 2.7
Classifier: Programming Language :: Python :: 3.4
Classifier: Programming Language :: Python :: 3
Requires-Python: >=2.7.0, !=3.0, !=3.1, !=3.2, !=3.3, <4
Requires-Dist: urllib3 (>=1.15)
Requires-Dist: six (>=1.10)
Requires-Dist: certifi
Requires-Dist: python-dateutil
